jupyter_innotater/__init__.py
jupyter_innotater/__meta__.py
jupyter_innotater/combine.py
jupyter_innotater/customwidgets.py
jupyter_innotater/data.py
jupyter_innotater/imagewidget.py
jupyter_innotater/innotaterwidget.py
jupyter_innotater/manager.py
jupyter_innotater/mixins.py
jupyter_innotater/uiinnotations.py
jupyter_innotater/watchlist.py
jupyter_innotater/labextension/package.json
jupyter_innotater/labextension/static/486.487fe385738e34498f81.js
jupyter_innotater/labextension/static/486.487fe385738e34498f81.js.LICENSE.txt
jupyter_innotater/labextension/static/568.3e47cce772f692f91fef.js
jupyter_innotater/labextension/static/568.882ba6b1320ccafd7142.js
jupyter_innotater/labextension/static/645.b4ca306c908fb1ce6d75.js
jupyter_innotater/labextension/static/645.b4ca306c908fb1ce6d75.js.LICENSE.txt
jupyter_innotater/labextension/static/713.2c10bae4a0c737c7899a.js
jupyter_innotater/labextension/static/755.c231febf2dabd55189df.js
jupyter_innotater/labextension/static/755.c231febf2dabd55189df.js.LICENSE.txt
jupyter_innotater/labextension/static/776.d07a78b8d14f05f91a8a.js
jupyter_innotater/labextension/static/remoteEntry.e73190058c9efcbe95f5.js
jupyter_innotater/labextension/static/remoteEntry.e8a99e83a731dfe19398.js
jupyter_innotater/labextension/static/style.js
jupyter_innotater/labextension/static/third-party-licenses.json
jupyter_innotater-0.3.1.data/data/share/jupyter/labextensions/jupyter-innotater/install.json
jupyter_innotater-0.3.1.data/data/share/jupyter/labextensions/jupyter-innotater/package.json
jupyter_innotater-0.3.1.data/data/share/jupyter/labextensions/jupyter-innotater/static/486.487fe385738e34498f81.js
jupyter_innotater-0.3.1.data/data/share/jupyter/labextensions/jupyter-innotater/static/486.487fe385738e34498f81.js.LICENSE.txt
jupyter_innotater-0.3.1.data/data/share/jupyter/labextensions/jupyter-innotater/static/568.3e47cce772f692f91fef.js
jupyter_innotater-0.3.1.data/data/share/jupyter/labextensions/jupyter-innotater/static/645.b4ca306c908fb1ce6d75.js
jupyter_innotater-0.3.1.dist-info/LICENSE
jupyter_innotater-0.3.1.dist-info/METADATA
jupyter_innotater-0.3.1.dist-info/WHEEL
jupyter_innotater-0.3.1.dist-info/top_level.txt
jupyter_innotater-0.3.1.dist-info/RECORD
