Metadata-Version: 2.1
Name: jupyter-innotater
Version: 0.3.1
Summary: An Inline Data Annotator for Jupyter
Home-page: https://github.com/ideonate/jupyter-innotater
Author: Dan Lester
Author-email: support@ideonate.com
License: BSD-3-Clause
Keywords: Jupyter,JupyterLab,JupyterLab3
Platform: Linux
Platform: Mac OS X
Platform: Windows
Classifier: License :: OSI Approved :: BSD License
Classifier: Programming Language :: Python
Classifier: Programming Language :: Python :: 3
Classifier: Programming Language :: Python :: 3.6
Classifier: Programming Language :: Python :: 3.7
Classifier: Programming Language :: Python :: 3.8
Classifier: Programming Language :: Python :: 3.9
Classifier: Framework :: Jupyter
Classifier: Framework :: Jupyter :: JupyterLab
Classifier: Framework :: Jupyter :: JupyterLab :: 3
Classifier: Framework :: Jupyter :: JupyterLab :: Extensions
Classifier: Framework :: Jupyter :: JupyterLab :: Extensions :: Prebuilt
Requires-Python: >=3.6
License-File: LICENSE
Requires-Dist: numpy (>=1.4.0)
Requires-Dist: pypng (>=0.0.19)
Requires-Dist: jupyterlab (~=3.0)
Requires-Dist: jupyter-packaging
Requires-Dist: ipywidgets (>=7.6.5)
